pons/__init__.py
pons/event_log.py
pons/message.py
pons/node.py
pons/simulation.py
pons/apps/__init__.py
pons/apps/app.py
pons/apps/ping.py
pons/apps/udpgw.py
pons/mobility/__init__.py
pons/mobility/movement.py
pons/mobility/ns2_parser.py
pons/net/__init__.py
pons/net/common.py
pons/net/netplan.py
pons/net/plans/__init__.py
pons/net/plans/core.py
pons/net/plans/ion.py
pons/routing/__init__.py
pons/routing/directdelivery.py
pons/routing/epidemic.py
pons/routing/firstcontact.py
pons/routing/prophet.py
pons/routing/router.py
pons/routing/sprayandwait.py
pons/routing/static.py
pons/utils/__init__.py
pons/utils/list_utils.py
pons/utils/misc.py
pons/utils/vector.py
netedit/Dockerfile
netedit/README.md
netedit/netedit.py
netedit/requirements.txt
netedit/run-in-docker.sh
netedit/docker/entrypoint.sh
netedit/docker/xstartup
netedit/gui/__init__.py
netedit/gui/dialogs.py
plot_contacts/plot_contacts.py
plot_contacts/requirements.txt
ponsanim/ponsanim.py
ponsanim/requirements.txt
scenariorunner/scenariohelper.py
scenariorunner/scenariorunner.py
pons_dtn-0.2.1.dist-info/METADATA
pons_dtn-0.2.1.dist-info/WHEEL
pons_dtn-0.2.1.dist-info/entry_points.txt
pons_dtn-0.2.1.dist-info/licenses/LICENSE
pons_dtn-0.2.1.dist-info/RECORD
