Metadata-Version: 2.4
Name: pons-dtn
Version: 0.2.1
Summary: The Python Opportunistic Network Simulator (PONS) is a discrete-event simulator for opportunistic/DTN networks.
Project-URL: Homepage, https://github.com/gh0st42/pons
Project-URL: Issues, https://github.com/gh0st42/pons/issues
Project-URL: Repository, https://github.com/gh0st42/pons.git
Author-email: Lars Baumgaertner <1264131+gh0st42@users.noreply.github.com>
License-File: LICENSE
Keywords: DTN,delay-tolerant networks,discrete-event simulation,disruption-tolerant networks,network simulation,networking,opportunistic networks,simulator
Classifier: Intended Audience :: Science/Research
Classifier: License :: OSI Approved :: MIT License
Classifier: Operating System :: OS Independent
Classifier: Programming Language :: Python :: 3
Classifier: Topic :: Communications
Requires-Python: >=3.9
Requires-Dist: matplotlib~=3.10.1
Requires-Dist: networkx~=3.3
Requires-Dist: pandas~=2.2.3
Requires-Dist: pillow~=10.4.0
Requires-Dist: python-dateutil~=2.9.0.post0
Requires-Dist: simpy~=4.1.1
Provides-Extra: mp4
Requires-Dist: opencv-python; extra == 'mp4'
